readtheyaml/__init__.py
readtheyaml/schema.py
readtheyaml/sections.py
readtheyaml/exceptions/__init__.py
readtheyaml/exceptions/format_error.py
readtheyaml/exceptions/validation_error.py
readtheyaml/fields/__init__.py
readtheyaml/fields/bool_field.py
readtheyaml/fields/composite_field.py
readtheyaml/fields/enum_field.py
readtheyaml/fields/field.py
readtheyaml/fields/field_helpers.py
readtheyaml/fields/field_registery.py
readtheyaml/fields/field_validation_helpers.py
readtheyaml/fields/list_field.py
readtheyaml/fields/none_field.py
readtheyaml/fields/numerical_field.py
readtheyaml/fields/string_field.py
readtheyaml/fields/tuple_field.py
readtheyaml/fields/union_field.py
readtheyaml-1.9.0.dist-info/licenses/LICENSE
tests/__init__.py
tests/test_composite_fields.py
tests/test_fields.py
tests/test_schema.py
readtheyaml-1.9.0.dist-info/METADATA
readtheyaml-1.9.0.dist-info/WHEEL
readtheyaml-1.9.0.dist-info/top_level.txt
readtheyaml-1.9.0.dist-info/RECORD
