Metadata-Version: 2.4
Name: ReadTheYAML
Version: 1.9.0
Summary: Validate and document your YAML config files — so future-you doesn't have to guess.
Author-email: Vincent Martineau <vincent.martineau.1@ulaval.ca>
License: MIT
Requires-Python: >=3.10
License-File: LICENSE
Requires-Dist: pyyaml>=6.0
Dynamic: license-file
